lingora/__init__.py
lingora/cli.py
lingora/sanic_app.py
lingora-1.0.3.dist-info/licenses/LICENSE
lingora-1.0.3.dist-info/METADATA
lingora-1.0.3.dist-info/WHEEL
lingora-1.0.3.dist-info/entry_points.txt
lingora-1.0.3.dist-info/top_level.txt
lingora-1.0.3.dist-info/RECORD
