Metadata-Version: 2.4
Name: lingora
Version: 1.0.3
Summary: A utility automating performing language transformations
Author-email: Isaak Engineer <isaak@schloosser.com>
License-Expression: AGPL-3.0-only
Project-URL: Homepage, https://git.schloosser.net/lingora/lingora
Project-URL: Issues, https://git.schloosser.net/lingora/lingora/issues
Classifier: Development Status :: 3 - Alpha
Classifier: Environment :: Console
Classifier: Intended Audience :: Developers
Classifier: Intended Audience :: End Users/Desktop
Classifier: Operating System :: OS Independent
Classifier: Programming Language :: Python :: 3
Classifier: Programming Language :: Python :: 3.8
Classifier: Programming Language :: Python :: 3.9
Classifier: Programming Language :: Python :: 3.10
Classifier: Topic :: Software Development :: Localization
Classifier: Topic :: Utilities
Requires-Python: >=3.8
License-File: LICENSE
Requires-Dist: typer
Requires-Dist: rich
Requires-Dist: sanic
Requires-Dist: openai
Requires-Dist: python-dotenv
Requires-Dist: requests
Requires-Dist: aiohttp
Requires-Dist: jinja2
Requires-Dist: websockets
Requires-Dist: cyrtranslit>=1.1.1
Provides-Extra: dev
Requires-Dist: pytest; extra == "dev"
Requires-Dist: black; extra == "dev"
Requires-Dist: flake8; extra == "dev"
Requires-Dist: mypy; extra == "dev"
Dynamic: license-file
